textql/__init__.py
textql/__init__.pyi
textql/client.py
textql/exceptions.py
textql/exceptions.pyi
textql/py.typed
textql/platform/__init__.py
textql-0.3.6.dist-info/METADATA
textql-0.3.6.dist-info/WHEEL
textql-0.3.6.dist-info/top_level.txt
textql-0.3.6.dist-info/RECORD
