Metadata-Version: 2.4
Name: textql
Version: 0.3.6
Summary: Python client library for TextQL
Author: TextQL Labs
Requires-Python: >=3.8
Requires-Dist: grpcio>=1.68.0
Requires-Dist: protobuf>=5.28.0
Provides-Extra: dev
Requires-Dist: grpcio-tools>=1.68.0; extra == "dev"
Requires-Dist: black; extra == "dev"
Requires-Dist: mypy; extra == "dev"
Requires-Dist: mypy-protobuf; extra == "dev"
Requires-Dist: ruff>=0.1.0; extra == "dev"
Requires-Dist: types-protobuf>=4.0.0; extra == "dev"
Dynamic: author
Dynamic: requires-python
